cp210x_scanner/CP210xManufacturing.py
cp210x_scanner/CP210xRuntime.py
cp210x_scanner/__about__.py
cp210x_scanner/__init__.py
cp210x_scanner/scanner.py
cp210x_scanner/lib/windows/arm/CP210xManufacturing.dll
cp210x_scanner/lib/windows/arm/CP210xRuntime.dll
cp210x_scanner/lib/windows/arm64/CP210xManufacturing.dll
cp210x_scanner/lib/windows/arm64/CP210xRuntime.dll
cp210x_scanner/lib/windows/x64/CP210xManufacturing.dll
cp210x_scanner/lib/windows/x64/CP210xRuntime.dll
cp210x_scanner/lib/windows/x86/CP210xManufacturing.dll
cp210x_scanner/lib/windows/x86/CP210xRuntime.dll
cp210x_scanner-0.0.1.dist-info/METADATA
cp210x_scanner-0.0.1.dist-info/WHEEL
cp210x_scanner-0.0.1.dist-info/licenses/LICENSE.txt
cp210x_scanner-0.0.1.dist-info/RECORD
